{
    "code": 200,
    "data": 
[
      {
        "sort": "10",
        "type": "特別活動",
        "startTime": 1512546308,
        "endTime": 1512576000,
        "eventStartTime": 1512403200,
        "eventEndTime": 1513612799,
        "externalUrl": "",
        "imgUrl": "http://d1d5g3a7mdfbpj.cloudfront.net/banner/20171204_815X315_08210ee2675e767b5dd78243d889d21a.jpg",
        "title": "全新修行挑戰『螻蟻的掙扎』",
        "info": "時間：12 月 5 日 (二) 至 12 月 18 日 (一)\r\n試圖吞噬一切的魔獸，只為追隨自我世界的真理！\r\n\r\n＊設有「六絃之首 ‧ 蒼」供召喚師無限兌換\r\n＊完成挑戰指定次數，可獲得「百世經綸 ‧ 一頁書」動態造型"
      },
      {
        "sort": "10",
        "type": "封印卡活動",
        "startTime": 1512546308,
        "endTime": 1512576000,
        "eventStartTime": 1512057600,
        "eventEndTime": 1513612799,
        "externalUrl": "",
        "imgUrl": "http://d1d5g3a7mdfbpj.cloudfront.net/banner/20171126_815X256_863e122bf8dfdee7c07e9971fe2e103b.jpg",
        "title": "魔法石封印卡活動『霹靂天石』",
        "info": "活動期間再度開放『霹靂天石』抽卡選項，當中包含 8 位『霹靂布袋戲』系列角色。\r\n同時，獲得稀有角色的機率將大幅提升。『霹靂天石』可於『商店』的『封印卡』內找到。\r\n\r\n時間：12 月 1 日 (五) 16:00 至 12 月 18 日 (一) 23:59\r\n\r\n『霹靂布袋戲』系列包括：\r\n6星 素還真\r\n6星 魔王子\r\n6星 劍之初\r\n6星 一頁書\r\n6星 葉小釵\r\n6星 戢武王\r\n6星 傲笑紅塵\r\n6星 風之痕\r\n\r\n＊ 此為『霹靂布袋戲』系列最後一次復刻，其後將不會再次開放"
      },
      {
        "sort": "10",
        "type": "封印卡活動",
        "startTime": 1512546308,
        "endTime": 1512576000,
        "eventStartTime": 1512316800,
        "eventEndTime": 1513871999,
        "externalUrl": "",
        "imgUrl": "http://d1d5g3a7mdfbpj.cloudfront.net/banner/20171130_815X256_2963fd6f61319fee8429f498f6105ae1.jpg",
        "title": "魔法石封印卡活動『起源刻紋』",
        "info": "時間：12 月 4 日 (一) 至 12 月 21 日 (日)\r\n活動期間開放『起源刻紋』抽卡選項，當中包含 8 位『宇宙序章』系列角色。\r\n『起源刻紋』可於『商店』內找到。\r\n\r\n『宇宙序章』系列包括：\r\n5 星 烏波 ‧ 薩斯拉\r\n5 星 格赫羅斯\r\n5 星 伊波 ‧ 茲特爾\r\n5 星 道羅斯\r\n5 星 阿撒托斯\r\n5 星 阿布霍斯\r\n5 星 加塔諾托亞\r\n5 星 阿特拉克 ‧ 納克亞\r\n"
      },
      {
        "sort": "20",
        "type": "儲值送好禮",
        "startTime": 1512546308,
        "endTime": 1512576000,
        "eventStartTime": 1512316800,
        "eventEndTime": 1512921599,
        "externalUrl": "",
        "imgUrl": "http://d1d5g3a7mdfbpj.cloudfront.net/banner/20171204_815X256_44c8bbdb965b6564a74246bdf47205c3.jpg",
        "title": "儲值送好禮",
        "info": "時間：12 月 4 日 (一) 至 12 月 10 日 (日)\r\n只要在活動期間首次單筆儲值魔法石 6 粒或以上(不論之前是否曾儲值），可額外獲得『宇宙序章』系列封印卡隨機一張，獲得之封印卡必定為技能等級 7 。同時，召喚師可獲贈『龍僕選擇券』1 隻。每位召喚師最多只會得到獎賞一次。\r\n"
      },
      {
        "sort": "20",
        "type": "特別活動",
        "startTime": 1512546308,
        "endTime": 1512576000,
        "eventStartTime": 1512057600,
        "eventEndTime": 1513612799,
        "externalUrl": "",
        "imgUrl": "http://d1d5g3a7mdfbpj.cloudfront.net/banner/20171126_815X256_90fd47261ec38c344660a977d288fce3.jpg",
        "title": "復刻任務『三教頂峰』系列",
        "info": "無人能出他們其右，準備領教三位掌門人的極致武學與俠義之道。\r\n\r\n時間：12 月 1 日 (五) 16:00 至 12 月 18 日 (一) 23:59\r\n\r\n註:\r\n1.『三教頂峰』系列設有精英級難度，成功通關後 BOSS 100% 掉落！\r\n2. 此為『三教頂峰』系列最後一次復刻，其後將不會再次開放"
      },
      {
        "sort": "30",
        "type": "特別活動",
        "startTime": 1512546308,
        "endTime": 1512576000,
        "eventStartTime": 1512057600,
        "eventEndTime": 1513612799,
        "externalUrl": "",
        "imgUrl": "http://d1d5g3a7mdfbpj.cloudfront.net/banner/20171126_815X256_35c1d3cec4e23e57059f231af8731de5.jpg",
        "title": "『霹靂布袋戲』稀有角色動態造型出場",
        "info": "活動期間，稀有角色們的動態造型將會出現於不同活動之中！\r\n\r\n時間：12 月 1 日 (五) 16:00 至 12 月 18 日 (一) 23:59\r\n\r\n「清香白蓮 ‧ 素還真」動態造型\r\n於指定封印卡匣進行抽卡動作，可獲得的全新動態造型！\r\n指定封印卡匣包括：『魔法石銘之封印（上）』『魔法石刻之封印（下）』『霹靂天石』『宇宙序章』\r\n\r\n＊ 此活動只適用於需要消耗魔法石的抽卡機會，獎賞派發的抽卡機會並不包括在內\r\n\r\n「刀狂劍痴 ‧ 葉小釵」動態造型\r\n將設於靈魂商店中，供召喚師購買！\r\n\r\n「百世經綸 ‧ 一頁書」動態造型\r\n將於下版本初期出現，敬請留意官方消息。"
      },
      {
        "sort": "30",
        "type": "儲值送好禮",
        "startTime": 1512546308,
        "endTime": 1512576000,
        "eventStartTime": 1512316800,
        "eventEndTime": 1513526399,
        "externalUrl": "",
        "imgUrl": "http://d1d5g3a7mdfbpj.cloudfront.net/banner/20171130_815X256_6b5eb6d6169b4b8f0ea4ce0443beb56c.jpg",
        "title": "儲值活動『好禮包成雙』",
        "info": "時間： 12 月 4 日 (一) 至 12 月 17 日 (日)\r\n活動期間將推出新一期「月禮包」儲值方案！召喚師可以優惠價格獲得大量魔法石與抽卡機會！另外，「龍刻武裝禮包」將同步登場，助你快速投入龍刻武裝全新力量！\r\n"
      },
      {
        "sort": "40",
        "type": "特別活動",
        "startTime": 1512546308,
        "endTime": 1512576000,
        "eventStartTime": 1512316800,
        "eventEndTime": 1512921599,
        "externalUrl": "",
        "imgUrl": "http://d1d5g3a7mdfbpj.cloudfront.net/banner/20171130_815X256_26069792f17233cba82e61036782e091.jpg",
        "title": "特別活動『認識未知的恐懼』",
        "info": "時間：12 月 4 日 (一) 至 12 月 10 日 (日)\r\n游走於創造與破壞之間，一起研究生命的起源！\r\n\r\n＊成功通過關卡可獲得「悖論創造 ‧ 道羅斯」動態造型與「武裝原料」1 粒\r\n＊召喚師可在重登遊戲後，於 [社群] → [獎賞] 中獲取"
      },
      {
        "sort": "40",
        "type": "特別活動",
        "startTime": 1512546308,
        "endTime": 1512576000,
        "eventStartTime": 1511712000,
        "eventEndTime": 1512921599,
        "externalUrl": "",
        "imgUrl": "http://d1d5g3a7mdfbpj.cloudfront.net/banner/20171126_815X256_3d0821f1ad9762f097e8a118eac85eb6.jpg",
        "title": "復刻任務『死物附靈』系列",
        "info": "活動期間『死物附靈』系列所有關卡將逐一開放，同時系列角色掉落率獲得提升！\r\n\r\n『物靈附身 ‧ 暗』－11 月 27 日 (一) 至 12 月 10 日 (日) "
      },
      {
        "sort": "50",
        "type": "特別活動",
        "startTime": 1512546308,
        "endTime": 1512576000,
        "eventStartTime": 1512316800,
        "eventEndTime": 1514735999,
        "externalUrl": "",
        "imgUrl": "http://d1d5g3a7mdfbpj.cloudfront.net/banner/20171130_815X256_6ed8dccf7d5c31729d571dd0a3807937.jpg",
        "title": "『宇宙序章』與『魔族始源』系列強化合成效果提升",
        "info": "時間：12 月 4 日 (一) 至 12 月 31 日 (日)\r\n活動期間，以上兩個系列進行強化合成時必定獲得超絕強化或完美強化！\r\n"
      },
      {
        "sort": "60",
        "type": "儲值送好禮",
        "startTime": 1512546308,
        "endTime": 1512576000,
        "eventStartTime": 1512316800,
        "eventEndTime": 1513612799,
        "externalUrl": "",
        "imgUrl": "http://d1d5g3a7mdfbpj.cloudfront.net/banner/20171204_815X256_2154e464273be98627f9d9589c869f46.jpg",
        "title": "『神州幻域』關卡道具掉落率提升",
        "info": "時間：12 月 4 日 (一) 至 12 月 18 日 (一)\r\n活動期間「神州幻域」中的所有關卡道具將加倍掉落，掌握最後時光與大俠們切磋！\r\n\r\n＊以上所有活動將於 14.3 版本更新完成後開始\r\n＊『霹靂布袋戲』系列合作活動將於 12 月 18 日 23:59 後結束，敬請留意。\r\n　└ 部份活動將不再出現，包括「神州幻域」故事模式、「霹靂天石」封印"
      },
      {
        "sort": "90",
        "type": "本周關卡",
        "startTime": 1512546308,
        "endTime": 1512576000,
        "eventStartTime": 1512316800,
        "eventEndTime": 1512921599,
        "externalUrl": "",
        "imgUrl": "",
        "title": "本周關卡",
        "info": "[本周關卡] 全新修行挑戰『螻蟻的掙扎』\r\n時間：12 月 5 日 (二) 至 12 月 18 日 (一)\r\n\r\n[本周關卡] 特別活動『認識未知的恐懼』\r\n時間：12 月 4 日 (一) 至 12 月 10 日 (日)\r\n\r\n[本周關卡]地獄級關卡『無盡的破壞』\r\n時間：12 月 8 日 (五) 22:00 至 12 月 10 日 (日) 23:59\r\n\r\n[本周關卡] 復刻任務『三教頂峰』系列\r\n時間：12 月 1 日 (五) 16:00 至 12 月 18 日 (一) 23:59\r\n\r\n[本周關卡] 復刻任務『物靈附身 ‧ 暗』\r\n時間：11 月 27 日 (一) 至 12 月 10 日 (日)\r\n\r\n[特許關卡]『遺跡特許』關卡售賣系統\r\n開放關卡包括：\r\n遺跡特許 ‧ 無貌之神的誓約\r\n遺跡特許 ‧ 命運少女史\r\n遺跡特許 ‧ 鎧之魂\r\n遺跡特許 ‧ 實現願望的代價\r\n遺跡特許 ‧ 守護犬大冒險\r\n遺跡特許 ‧ 異變的永生\r\n遺跡特許 ‧ 妖相迷惑\r\n遺跡特許 ‧ 魔境的審判\r\n遺跡特許 ‧ 眾喃之耳\r\n遺跡特許 ‧ 龍焰重燃\r\n遺跡特許 ‧ 塔之門衛\r\n遺跡特許 ‧ 魔研結晶\r\n遺跡特許 ‧ 黃衣之王的印記\r\n遺跡特許 ‧ 強大的火力支援\r\n遺跡特許 ‧ 防患龍跡\r\n遺跡特許 ‧ 超獸總司令\r\n遺跡特許 ‧ 忠誠的千知鴞鳥\r\n遺跡特許 ‧ 代表力量的翅膀\r\n遺跡特許 ‧ 水惡鬼的血契\r\n遺跡特許 ‧ 火惡鬼的血契\r\n遺跡特許 ‧ 木惡鬼的血契\r\n遺跡特許 ‧ 光惡鬼的血契\r\n遺跡特許 ‧ 暗惡鬼的血契\r\n遺跡特許 ‧ 老師遺留的紀錄\r\n遺跡特許 ‧ 東方靈獸傳記\r\n遺跡特許 ‧ 玉清之主來臨\r\n遺跡特許 ‧ 上清教主降尊\r\n遺跡特許 ‧ 太清尊者降生\r\n遺跡特許 ‧ 與摩斯路並肩而戰\r\n遺跡特許 ‧ 與薇薇爾並肩而戰\r\n遺跡特許 ‧ 與毒刺並肩而戰\r\n遺跡特許 ‧ 與皮諾曹並肩而戰\r\n遺跡特許 ‧ 與傑佩諾並肩而戰\r\n遺跡特許 ‧ 瘦長身影的傳說\r\n遺跡特許 ‧ 暴食之罪\r\n遺跡特許 ‧ 貪婪之罪\r\n遺跡特許 ‧ 狂怒之罪\r\n遺跡特許 ‧ 色慾之罪\r\n遺跡特許 ‧ 傲慢之罪\r\n遺跡特許 ‧ 怠惰之罪\r\n遺跡特許 ‧ 嫉妒之罪\r\n遺跡特許 ‧ 瘋癲的茶客\r\n遺跡特許 ‧ 狂人的茶會\r\n遺跡特許 ‧ 墮進魔境之洞\r\n遺跡特許 ‧ 被喚醒的睡獸\r\n遺跡特許 ‧ 魔境的岔路\r\n遺跡特許 ‧ 一諾千金\r\n遺跡特許 ‧ 無貌之神的誓約\r\n遺跡特許 ‧ 實現願望的代價\r\n遺跡特許 ‧ 異變的永生\r\n遺跡特許 ‧ 魔境的審判"
      },],
}
